flask_optimize/__init__.py
flask_optimize/optimize.py
flask_optimize-0.2.9.8.dist-info/METADATA
flask_optimize-0.2.9.8.dist-info/RECORD
flask_optimize-0.2.9.8.dist-info/WHEEL
flask_optimize-0.2.9.8.dist-info/top_level.txt
