Metadata-Version: 2.1
Name: flask-optimize
Version: 0.2.9.8
Summary: Flask optimization using cache, minify html and compress response
Home-page: https://github.com/sunary/flask-optimize
Author: Sunary [Nhat Vo Van]
Author-email: v2nhat@gmail.com
Maintainer: Sunary [Nhat Vo Van]
Maintainer-email: v2nhat@gmail.com
License: All code is released under the MIT License:
Requires-Dist: Flask (>=0.10.1)
Requires-Dist: htmlmin (>=0.1.10)
